{
  "enrolledList": [
    { "name": "Prakhar Tandon" },
    { "name": "Mukul Dubey" },
    { "name": "Rohan Singh" },
    { "name": "Aishwarya Gupta" },
    { "name": "Neha Kumar" },
    { "name": "Priya Sharma" },
    { "name": "Vikram Singh" },
    { "name": "Ananya Das" },
    { "name": "Rajesh Verma" },
    { "name": "Sneha Mishra" },
    { "name": "Amit Tiwari" },
    { "name": "Shreya Singh" },
    { "name": "Ankit Kumar" },
    { "name": "Divya Gupta" },
    { "name": "Vivek Singh" },
    { "name": "Kritika Sharma" },
    { "name": "Arjun Singh" },
    { "name": "Tanvi Patel" },
    { "name": "Sachin Yadav" },
    { "name": "Nisha Gupta" },
    { "name": "Aditya Sharma" },
    { "name": "Pooja Singh" },
    { "name": "Deepak Verma" },
    { "name": "Anjali Sharma" },
    { "name": "Rahul Gupta" },
    { "name": "Sonia Singh" },
    { "name": "Harshita Patel" },
    { "name": "Alok Kumar" },
    { "name": "Swati Sharma" }
  ]
}
